{
  "name": "MSExportSheetItem",
  "extends": "NSCollectionViewItem",
  "interfaces": [],
  "methods": {},
  "properties": {
    "previewContainer": {
      "name": "previewContainer",
      "pointer": false,
      "type": "IBOutlet NSView ",
      "attributes": [
        "nonatomic",
        "strong"
      ]
    },
    "checkBox": {
      "name": "checkBox",
      "pointer": false,
      "type": "IBOutlet NSButton ",
      "attributes": [
        "nonatomic",
        "strong"
      ]
    },
    "warningView": {
      "name": "warningView",
      "pointer": false,
      "type": "IBOutlet NSImageView ",
      "attributes": [
        "nonatomic",
        "strong"
      ]
    },
    "exportSheet": {
      "name": "exportSheet",
      "pointer": false,
      "type": "MSExportSheet ",
      "attributes": [
        "nonatomic",
        "weak"
      ]
    },
    "showWarningLabel": {
      "name": "showWarningLabel",
      "pointer": false,
      "type": "BOOL",
      "attributes": [
        "nonatomic",
        "assign"
      ]
    },
    "isExportable": {
      "name": "isExportable",
      "pointer": false,
      "type": "BOOL",
      "attributes": [
        "nonatomic",
        "assign"
      ]
    }
  },
  "generics": []
}