{
  "name": "_SVGStroke",
  "extends": "SVGElement",
  "interfaces": [],
  "methods": {
    "propertyNames": {
      "name": "propertyNames",
      "bridgedName": "propertyNames",
      "args": [],
      "returns": "NSArray*",
      "kind": "class",
      "kindIndicator": "+"
    },
    "relationshipNames": {
      "name": "relationshipNames",
      "bridgedName": "relationshipNames",
      "args": [],
      "returns": "NSArray*",
      "kind": "class",
      "kindIndicator": "+"
    },
    "attributeNames": {
      "name": "attributeNames",
      "bridgedName": "attributeNames",
      "args": [],
      "returns": "NSArray*",
      "kind": "class",
      "kindIndicator": "+"
    },
    "primitiveSetGradient:": {
      "name": "primitiveSetGradient:",
      "bridgedName": "primitiveSetGradient",
      "args": [
        {
          "name": "gradient",
          "type": "id",
          "nullable": false
        }
      ],
      "returns": "void",
      "kind": "instance",
      "kindIndicator": "-"
    },
    "primitiveSetPattern:": {
      "name": "primitiveSetPattern:",
      "bridgedName": "primitiveSetPattern",
      "args": [
        {
          "name": "pattern",
          "type": "id",
          "nullable": false
        }
      ],
      "returns": "void",
      "kind": "instance",
      "kindIndicator": "-"
    },
    "primitiveAddUsedByObject:": {
      "name": "primitiveAddUsedByObject:",
      "bridgedName": "primitiveAddUsedByObject",
      "args": [
        {
          "name": "object",
          "type": "id",
          "nullable": false
        }
      ],
      "returns": "void",
      "kind": "instance",
      "kindIndicator": "-"
    },
    "primitiveRemoveUsedByObject:": {
      "name": "primitiveRemoveUsedByObject:",
      "bridgedName": "primitiveRemoveUsedByObject",
      "args": [
        {
          "name": "object",
          "type": "id",
          "nullable": false
        }
      ],
      "returns": "void",
      "kind": "instance",
      "kindIndicator": "-"
    }
  },
  "properties": {
    "color": {
      "name": "color",
      "pointer": false,
      "type": "MSImmutableColor*",
      "attributes": [
        "strong",
        "nonatomic"
      ]
    },
    "dashes": {
      "name": "dashes",
      "pointer": false,
      "type": "NSArray*",
      "attributes": [
        "strong",
        "nonatomic"
      ]
    },
    "linecap": {
      "name": "linecap",
      "pointer": false,
      "type": "NSString*",
      "attributes": [
        "strong",
        "nonatomic"
      ]
    },
    "linejoin": {
      "name": "linejoin",
      "pointer": false,
      "type": "NSString*",
      "attributes": [
        "strong",
        "nonatomic"
      ]
    },
    "width": {
      "name": "width",
      "pointer": false,
      "type": "double",
      "attributes": [
        "assign",
        "nonatomic"
      ]
    },
    "gradient": {
      "name": "gradient",
      "pointer": false,
      "type": "SVGGradient*",
      "attributes": [
        "strong",
        "nonatomic"
      ]
    },
    "pattern": {
      "name": "pattern",
      "pointer": false,
      "type": "SVGPattern*",
      "attributes": [
        "strong",
        "nonatomic"
      ]
    },
    "usedBy": {
      "name": "usedBy",
      "pointer": false,
      "type": "NSSet*",
      "attributes": [
        "strong",
        "nonatomic"
      ]
    }
  },
  "generics": []
}