{
  "name": "MSShapePath",
  "extends": "_MSShapePath",
  "interfaces": [
    "MSShapePath"
  ],
  "methods": {
    "pathWithPoints:": {
      "name": "pathWithPoints:",
      "bridgedName": "pathWithPoints",
      "args": [
        {
          "name": "points",
          "type": "NSArray *",
          "nullable": false
        }
      ],
      "returns": "id",
      "kind": "class",
      "kindIndicator": "+"
    },
    "initWithPoints:": {
      "name": "initWithPoints:",
      "bridgedName": "initWithPoints",
      "args": [
        {
          "name": "points",
          "type": "NSArray *",
          "nullable": false
        }
      ],
      "returns": "id",
      "kind": "instance",
      "kindIndicator": "-"
    },
    "pathWithBezierPath:inRect:": {
      "name": "pathWithBezierPath:inRect:",
      "bridgedName": "pathWithBezierPath_inRect",
      "args": [
        {
          "name": "bezierPath",
          "type": "NSBezierPath *",
          "nullable": false
        },
        {
          "name": "rect",
          "type": "NSRect",
          "nullable": false
        }
      ],
      "returns": "id",
      "kind": "class",
      "kindIndicator": "+"
    },
    "initWithBezierPath:inRect:": {
      "name": "initWithBezierPath:inRect:",
      "bridgedName": "initWithBezierPath_inRect",
      "args": [
        {
          "name": "bezierPath",
          "type": "NSBezierPath *",
          "nullable": false
        },
        {
          "name": "rect",
          "type": "NSRect",
          "nullable": false
        }
      ],
      "returns": "id",
      "kind": "instance",
      "kindIndicator": "-"
    },
    "removeLastPoint": {
      "name": "removeLastPoint",
      "bridgedName": "removeLastPoint",
      "args": [],
      "returns": "void",
      "kind": "instance",
      "kindIndicator": "-"
    },
    "removeAllPoints": {
      "name": "removeAllPoints",
      "bridgedName": "removeAllPoints",
      "args": [],
      "returns": "void",
      "kind": "instance",
      "kindIndicator": "-"
    },
    "firstPoint": {
      "name": "firstPoint",
      "bridgedName": "firstPoint",
      "args": [],
      "returns": "MSCurvePoint *",
      "kind": "instance",
      "kindIndicator": "-"
    },
    "lastPoint": {
      "name": "lastPoint",
      "bridgedName": "lastPoint",
      "args": [],
      "returns": "MSCurvePoint *",
      "kind": "instance",
      "kindIndicator": "-"
    },
    "pointAtIndex:": {
      "name": "pointAtIndex:",
      "bridgedName": "pointAtIndex",
      "args": [
        {
          "name": "index",
          "type": "NSInteger",
          "nullable": false
        }
      ],
      "returns": "MSCurvePoint *",
      "kind": "instance",
      "kindIndicator": "-"
    },
    "pointsAroundIndex:": {
      "name": "pointsAroundIndex:",
      "bridgedName": "pointsAroundIndex",
      "args": [
        {
          "name": "index",
          "type": "NSUInteger",
          "nullable": false
        }
      ],
      "returns": "NSArray <MSCurvePoint*> *",
      "kind": "instance",
      "kindIndicator": "-"
    },
    "isLine": {
      "name": "isLine",
      "bridgedName": "isLine",
      "args": [],
      "returns": "BOOL",
      "kind": "instance",
      "kindIndicator": "-"
    },
    "isRectangle": {
      "name": "isRectangle",
      "bridgedName": "isRectangle",
      "args": [],
      "returns": "BOOL",
      "kind": "instance",
      "kindIndicator": "-"
    },
    "isPolygon": {
      "name": "isPolygon",
      "bridgedName": "isPolygon",
      "args": [],
      "returns": "BOOL",
      "kind": "instance",
      "kindIndicator": "-"
    },
    "simplifyPath": {
      "name": "simplifyPath",
      "bridgedName": "simplifyPath",
      "args": [],
      "returns": "void",
      "kind": "instance",
      "kindIndicator": "-"
    },
    "multiplyBy:": {
      "name": "multiplyBy:",
      "bridgedName": "multiplyBy",
      "args": [
        {
          "name": "amount",
          "type": "CGFloat",
          "nullable": false
        }
      ],
      "returns": "void",
      "kind": "instance",
      "kindIndicator": "-"
    }
  },
  "properties": {},
  "generics": []
}